ProbDists_nm
