Metadata-Version: 1.0
Name: ProbDists-nm
Version: 0.3
Summary: Gaussian/Binomial distributions
Home-page: UNKNOWN
Author: Niklas Muennighoff
Author-email: n.muennighoff@gmail.com
License: UNKNOWN
Platform: UNKNOWN
